[
    {
        "@context": "http://schema.org",
        "@type": "BreadcrumbList",
        "itemListElement": [
            {
                "@type": "ListItem",
                "position": 1,
                "item": {
                    "@id": "https://www.allrecipes.com/",
                    "name": "Home",
                    "image": null
                }
            },
            {
                "@type": "ListItem",
                "position": 2,
                "item": {
                    "@id": "https://www.allrecipes.com/recipes/",
                    "name": "Recipes",
                    "image": null
                }
            },
            {
                "@type": "ListItem",
                "position": 3,
                "item": {
                    "@id": "https://www.allrecipes.com/recipes/86/world-cuisine/",
                    "name": "World Cuisine",
                    "image": null
                }
            },
            {
                "@type": "ListItem",
                "position": 4,
                "item": {
                    "@id": "https://www.allrecipes.com/recipes/237/world-cuisine/latin-american/",
                    "name": "Latin American",
                    "image": null
                }
            },
            {
                "@type": "ListItem",
                "position": 5,
                "item": {
                    "@id": "https://www.allrecipes.com/recipes/728/world-cuisine/latin-american/mexican/",
                    "name": "Mexican",
                    "image": null
                }
            }
        ]
    },
    {
        "@context": "http://schema.org",
        "@type": "Recipe",
        "mainEntityOfPage": "https://www.allrecipes.com/recipe/221221/chocolate-pralines-mexican-style/",
        "name": "Chocolate Pralines, Mexican Style",
        "image": {
            "@type": "ImageObject",
            "url": "https://imagesvc.meredithcorp.io/v3/mm/image?url=https%3A%2F%2Fimages.media-allrecipes.com%2Fuserphotos%2F822860.jpg",
            "width": 3264,
            "height": 2448
        },
        "datePublished": "2020-06-19T03:48:22.000Z",
        "description": "These are the kind of pralines that you find at the checkout in Mexican restaurants. They are creamy instead of chewy like those in New Orleans, and the secret ingredient to make these creamy dreamy pralines...marshmallows! These are surprisingly easy to make and even quicker to disappear!",
        "prepTime": "P0DT0H20M",
        "cookTime": "P0DT0H20M",
        "totalTime": "P0DT1H40M",
        "recipeYield": "3 dozen pralines",
        "recipeIngredient": [
            "1\u2009\u00bd cups white sugar",
            "\u00bd cup packed light brown sugar",
            "\u00bd cup evaporated whole milk",
            "3 tablespoons light corn syrup",
            "1 tablespoon unsweetened cocoa powder",
            "4 large marshmallows",
            "\u00bd teaspoon vanilla extract",
            "2 teaspoons butter",
            "2 cups chopped pecans"
        ],
        "recipeInstructions": [
            {
                "@type": "HowToStep",
                "text": "Line a baking sheet with parchment paper.\n"
            },
            {
                "@type": "HowToStep",
                "text": "Stir white sugar, light brown sugar, evaporated milk, corn syrup, and cocoa powder in a saucepan and bring the mixture to a full rolling boil over medium heat. Reduce heat to medium low and cook, stirring constantly, until the syrup reaches 220 degrees F (104 degrees C) when measured with a candy thermometer. A small amount of syrup dropped into cold water should form a soft ball that flattens when removed from the water and placed on a flat surface.\n"
            },
            {
                "@type": "HowToStep",
                "text": "Remove pan from heat and stir in marshmallows, vanilla extract, butter, and pecans, beating the candy by hand until creamy and the candy begins to to set up slightly at the edges of the pan, about 10 minutes.\n"
            },
            {
                "@type": "HowToStep",
                "text": "Drop the warm candy by teaspoons onto the parchment paper; allow room for pralines to spread slightly. Cool the candy thoroughly before serving.\n"
            }
        ],
        "recipeCategory": [
            "World Cuisine",
            "Latin American",
            "Mexican"
        ],
        "recipeCuisine": [
            "Latin American",
            "Mexican"
        ],
        "author": [
            {
                "@type": "Person",
                "name": "mintconditionherbfarm"
            }
        ],
        "aggregateRating": {
            "@type": "AggregateRating",
            "ratingValue": 4.857142857142857,
            "ratingCount": 7,
            "itemReviewed": "Chocolate Pralines, Mexican Style",
            "bestRating": "5",
            "worstRating": "1"
        },
        "nutrition": {
            "@type": "NutritionInformation",
            "calories": "100.3 calories",
            "carbohydrateContent": "14.6 g",
            "cholesterolContent": "1.6 mg",
            "fatContent": "4.9 g",
            "fiberContent": "0.6 g",
            "proteinContent": "0.8 g",
            "saturatedFatContent": "0.7 g",
            "servingSize": null,
            "sodiumContent": "7.9 mg",
            "sugarContent": "12.8 g",
            "transFatContent": null,
            "unsaturatedFatContent": null
        },
        "review": [
            {
                "@type": "Review",
                "datePublished": "2012-10-19T13:55:17.83Z",
                "reviewBody": "i thought itr was good",
                "reviewRating": {
                    "@type": "Rating",
                    "worstRating": "1",
                    "bestRating": "5",
                    "ratingValue": 5
                },
                "author": {
                    "@type": "Person",
                    "name": "sky2013",
                    "image": null,
                    "sameAs": "https://www.allrecipes.com/cook/10113698/"
                }
            },
            {
                "@type": "Review",
                "datePublished": "2013-11-27T04:57:26.587Z",
                "reviewBody": "Wanted to make pralines for my mother-in-law. Have been trying a lot of praline recipes this was the 3rd try--home run! My husband doesn't like pralines but thought these were great. It helps to have more complete directions too. I did add 1t. cinnamon since they were Mexican and I love cinnamon in my chocolate-and doubled the cocoa since I like darker chocolate!",
                "reviewRating": {
                    "@type": "Rating",
                    "worstRating": "1",
                    "bestRating": "5",
                    "ratingValue": 5
                },
                "author": {
                    "@type": "Person",
                    "name": "george61",
                    "image": null,
                    "sameAs": "https://www.allrecipes.com/cook/12427191/"
                }
            },
            {
                "@type": "Review",
                "datePublished": "2019-06-22T06:18:07.47Z",
                "reviewBody": "The first time I made this I made it as written. It was good but you couldn't taste the chocolate - they just tasted like pralines. The next time I used 1/3 cup of cocoa instead of 1 T. OMG - they were AMAZING and so chocolatey!!!",
                "reviewRating": {
                    "@type": "Rating",
                    "worstRating": "1",
                    "bestRating": "5",
                    "ratingValue": 4
                },
                "author": {
                    "@type": "Person",
                    "name": "drprentice",
                    "image": null,
                    "sameAs": "https://www.allrecipes.com/cook/7489292/"
                }
            },
            {
                "@type": "Review",
                "datePublished": "2013-08-16T19:26:27.607Z",
                "reviewBody": "I took this to work for a Mexican theme luncheon and everyone loved it! I have requests for it frequently and everyone wants the recipe! Made it as written. Thanks!",
                "reviewRating": {
                    "@type": "Rating",
                    "worstRating": "1",
                    "bestRating": "5",
                    "ratingValue": 5
                },
                "author": {
                    "@type": "Person",
                    "name": "tdoss",
                    "image": null,
                    "sameAs": "https://www.allrecipes.com/cook/7546641/"
                }
            },
            {
                "@type": "Review",
                "datePublished": "2013-02-12T19:37:02.917Z",
                "reviewBody": "So yummy fast and easy! i added 1 teaspoon cinnamon (everything sweet is better with cinn). takes 20 mins to make 10 min to set up = ready to eat in 30 mins! Ingredients are basic staple items! Made them for son's Mardi Gras party at school and was thankful to find this recipe as he of course forgot to tell me he needed a treat for school party the next morning.:)",
                "reviewRating": {
                    "@type": "Rating",
                    "worstRating": "1",
                    "bestRating": "5",
                    "ratingValue": 5
                },
                "author": {
                    "@type": "Person",
                    "name": "Anita Ballul McGuire",
                    "image": null,
                    "sameAs": "https://www.allrecipes.com/cook/10924324/"
                }
            },
            {
                "@type": "Review",
                "datePublished": "2015-07-17T21:06:36.46Z",
                "reviewBody": "I added just a pinch of chipotle chili pepper along with the initial ingredients and once placed on parchment paper dusted with a pinch of coarse sea salt.... both of those combined gave it just a hint of heat and the salt cut the sweetness at just the right amount. Delish!",
                "reviewRating": {
                    "@type": "Rating",
                    "worstRating": "1",
                    "bestRating": "5",
                    "ratingValue": 5
                },
                "author": {
                    "@type": "Person",
                    "name": "Andrea Shawver Gardner",
                    "image": null,
                    "sameAs": "https://www.allrecipes.com/cook/214376/"
                }
            },
            {
                "@type": "Review",
                "datePublished": "2017-05-03T03:54:14.597Z",
                "reviewBody": "This is pretty tasty. As per some other reviewers I added cinnamon. I think the 10 min stirring at the end might be a little long. I didn't do it that long and it was already setting as I was getting them onto the cookie sheet. It didn't spread at all.",
                "reviewRating": {
                    "@type": "Rating",
                    "worstRating": "1",
                    "bestRating": "5",
                    "ratingValue": 5
                },
                "author": {
                    "@type": "Person",
                    "name": "motherbear",
                    "image": null,
                    "sameAs": "https://www.allrecipes.com/cook/8026900/"
                }
            }
        ]
    }
]